gcpinventory/__init__.py
gcpinventory/assigner.py
gcpinventory/models.py
gcpinventory/version.py
pygcpinventory-0.1.0.dist-info/licenses/LICENSE
pygcpinventory-0.1.0.dist-info/METADATA
pygcpinventory-0.1.0.dist-info/WHEEL
pygcpinventory-0.1.0.dist-info/top_level.txt
pygcpinventory-0.1.0.dist-info/RECORD
