Metadata-Version: 2.4
Name: pygcpinventory
Version: 0.1.0
Summary: GCP Project Inventory Collection Library
Author-email: OpenMetadata Integration Team <integration@openmetadata.org>
License: Apache-2.0
Project-URL: Homepage, https://github.com/open-metadata/openmetadata
Project-URL: Documentation, https://github.com/open-metadata/openmetadata
Project-URL: Repository, https://github.com/open-metadata/openmetadata
Project-URL: Issues, https://github.com/open-metadata/openmetadata/issues
Keywords: gcp,google-cloud,metadata,inventory,etl,bigquery,cloud-scheduler
Classifier: Development Status :: 3 - Alpha
Classifier: Intended Audience :: Developers
Classifier: License :: OSI Approved :: Apache Software License
Classifier: Operating System :: OS Independent
Classifier: Programming Language :: Python :: 3
Classifier: Programming Language :: Python :: 3.9
Classifier: Programming Language :: Python :: 3.10
Classifier: Programming Language :: Python :: 3.11
Classifier: Topic :: Software Development :: Libraries :: Python Modules
Requires-Python: >=3.9
License-File: LICENSE
Requires-Dist: google-api-python-client>=2.126.0
Requires-Dist: google-auth>=2.29.0
Requires-Dist: google-cloud-asset>=3.26.1
Requires-Dist: google-cloud-bigquery>=3.20.1
Requires-Dist: google-cloud-functions>=1.14.2
Requires-Dist: google-cloud-pubsub>=2.20.0
Requires-Dist: google-cloud-scheduler>=2.13.4
Requires-Dist: protobuf>=4.25.3
Requires-Dist: googleapis-common-protos>=1.63.0
Dynamic: license-file
